README.rst
setup.cfg
setup.py
src/ez_setup.py
src/AppiumLibrary/__init__.py
src/AppiumLibrary/version.py
src/AppiumLibrary/keywords/__init__.py
src/AppiumLibrary/keywords/_android_utils.py
src/AppiumLibrary/keywords/_applicationmanagement.py
src/AppiumLibrary/keywords/_element.py
src/AppiumLibrary/keywords/_keyevent.py
src/AppiumLibrary/keywords/_logging.py
src/AppiumLibrary/keywords/_mobilekeywords.py
src/AppiumLibrary/keywords/_runonfailure.py
src/AppiumLibrary/keywords/_screenshot.py
src/AppiumLibrary/keywords/_touch.py
src/AppiumLibrary/keywords/_waiting.py
src/AppiumLibrary/keywords/keywordgroup.py
src/AppiumLibrary/locators/__init__.py
src/AppiumLibrary/locators/elementfinder.py
src/AppiumLibrary/utils/__init__.py
src/AppiumLibrary/utils/applicationcache.py
src/AppiumLibrary/utils/librarylistener.py
src/AppiumLibrary/utils/events/__init__.py
src/AppiumLibrary/utils/events/event.py
src/AppiumLibrary/utils/events/scope_event.py
src/mobilelibrary.egg-info/PKG-INFO
src/mobilelibrary.egg-info/SOURCES.txt
src/mobilelibrary.egg-info/dependency_links.txt
src/mobilelibrary.egg-info/requires.txt
src/mobilelibrary.egg-info/top_level.txt