Metadata-Version: 1.1
Name: mobilelibrary
Version: 2.0.0
Summary: app testing library for Robot Framework Extended with AppiumLibrary
Home-page: https://g.hz.netease.com/yixinplusQA/RFUI_Framework/tree/master/Third-Party-Module/MobileLibrary
Author: Subscription QA
Author-email: <longmazhanfeng@gmail.com>
License: Apache License 2.0
Keywords: robotframework testing testautomation mobile appium webdriver app
Platform: any
Classifier: Development Status :: 5 - Production/Stable
Classifier: License :: OSI Approved :: Apache Software License
Classifier: Operating System :: OS Independent
Classifier: Programming Language :: Python
Classifier: Topic :: Software Development :: Testing
